hin/__init__.py
hin/__main__.py
hin/_actions.py
hin/_add.py
hin/_clone.py
hin/_commit.py
hin/_config.py
hin/_decorators.py
hin/_file.py
hin/_gitignore.py
hin/_link.py
hin/_list.py
hin/_main.py
hin/_push.py
hin/_remove.py
hin/_status.py
hin/_undo.py
hin/_version.py
hin/py.typed
hin-0.3.1.dist-info/LICENSE
hin-0.3.1.dist-info/METADATA
hin-0.3.1.dist-info/WHEEL
hin-0.3.1.dist-info/entry_points.txt
hin-0.3.1.dist-info/RECORD
