Metadata-Version: 2.1
Name: hin
Version: 0.3.1
Summary: Dotfile manager
Home-page: https://pypi.org/project/hin/
License: MIT
Keywords: config,dot,dotfile,file,hin
Author: jshwi
Author-email: stephen@jshwisolutions.com
Maintainer: jshwi
Maintainer-email: stephen@jshwisolutions.com
Requires-Python: >=3.8,<4.0
Classifier: License :: OSI Approved :: MIT License
Classifier: Programming Language :: Python :: 3
Classifier: Programming Language :: Python :: 3.8
Classifier: Programming Language :: Python :: 3.9
Classifier: Programming Language :: Python :: 3.10
Classifier: Programming Language :: Python :: 3.11
Requires-Dist: appdirs (>=1.4.4,<2.0.0)
Requires-Dist: click (>=8.1.3,<9.0.0)
Requires-Dist: click-help-colors (>=0.9.1,<0.10.0)
Requires-Dist: configobj (>=5.0.8,<6.0.0)
Requires-Dist: gitpython (>=3.1.31,<4.0.0)
Requires-Dist: rich (>=13.3.5,<14.0.0)
Project-URL: Documentation, https://hin.readthedocs.io/en/latest
Project-URL: Repository, https://github.com/jshwi/hin
